arxivapi/arxiv_paper.py
arxivapi/print_status.py
arxivapi/query.py
arxivquery-1.0.5.dist-info/LICENSE
arxivquery-1.0.5.dist-info/METADATA
arxivquery-1.0.5.dist-info/WHEEL
arxivquery-1.0.5.dist-info/top_level.txt
arxivquery-1.0.5.dist-info/RECORD
